[{"href": "/bbs/thread/3cdb5335004c6647/69728695-1.html", "topic": "\r\n\u505c\u8def\u8fb9\u53bb\u8d85\u5e02\u4e70\u4e1c\u897f\uff0c\u51fa\u6765\u8f66\u88ab\u4eba\u522e\u4e86\uff0c5\u4e2a\u6f06\u9762\u4e0d\u77e5\u9053\u80fd\u4e0d\u80fd\u641e\u5b9a            ", "author": ["//i.autohome.com.cn/55337254", "\u6d77\u54e5V"], "create_at": "2017-12-26", "reply_count": "23"}, {"href": "/bbs/thread/e5a286c160954329/69719152-1.html", "topic": "\r\n\u5c31\u8fd9\u6837\u522e\u64e6\uff0c\u6253\u7b97\u4e0d\u8d70\u4fdd\u9669\u4e86            ", "author": ["//i.autohome.com.cn/53961402", "\u6e05\u9192\u65f6\u597d\u7d2f"], "create_at": "2017-12-26", "reply_count": "7"}, {"href": "/bbs/thread/ad67e01649ee64ee/69708998-1.html", "topic": "\r\n\u8f66\u53cb\u5c0f\u805a\u5f52\u6765            ", "author": ["//i.autohome.com.cn/17425996", "\u5fc3\u7cfb\u767d\u9a6c"], "create_at": "2017-12-26", "reply_count": "5"}, {"href": "/bbs/thread/16f2749c7f996dbc/69631255-1.html", "topic": "\r\n\u6c42\u52a9\uff1a\u66f4\u6362LED\u8fd1\u5149\u706f\u540e\u539f\u8f66\u900f\u955c\u5207\u7ebf\u7684\u95ee\u9898            ", "author": ["//i.autohome.com.cn/8146418", "ly445621196"], "create_at": "2017-12-23", "reply_count": "8"}, {"href": "/bbs/thread/ddf5fff55ebfa0a1/69737197-1.html", "topic": "\r\n\u6709\u4e2d\u5c71\ufffd\ufffd\u53cb\ufffd\ufffd\ufffd\ufffd            ", "author": ["//i.autohome.com.cn/58751431", "YuMing01"], "create_at": "2017-12-26", "reply_count": "3"}, {"href": "/bbs/thread/a65cb9b03f0545a0/69691574-1.html", "topic": "\r\n\u6c42\u95ee \u6e29\u5dde\u601d\u57df\u662f\u5426\u52a0\u4ef7  \u5177\u4f53\u843d\u5730\u4ef7\u683c \u8c22\u8c22\u5404\u4f4d\uff01            ", "author": ["//i.autohome.com.cn/64876822", "XIN649236523"], "create_at": "2017-12-25", "reply_count": "3"}, {"href": "/bbs/thread/6d16e3ebb71ee778/69709818-1.html", "topic": "\r\n\u5404\u4f4d\u6362\u6c19\u6c14\u706f\u6ce1\u7684\u8001\u94c1\uff0c\u4f60\u4eec\u7684\u5b89\u5b9a\u600e\u4e48\u653e\u7684\u3002\u6700\u597d\u6709\u56fe\u7247            ", "author": ["//i.autohome.com.cn/24500233", "\u65e0\u540d\u6307\u7684\u56f0\u60d1"], "create_at": "2017-12-26", "reply_count": "4"}, {"href": "/bbs/thread/30eaf863df6a77e7/69707032-1.html", "topic": "\r\n\u8bf7\u95ee\u4f5b\u5c71\u798f\u514b\u65af1.5\u7684\u7cbe\u82f1\u7248\u843d\u5730\u591a\u5c11\u94b1            ", "author": ["//i.autohome.com.cn/19875664", "464257932"], "create_at": "2017-12-25", "reply_count": "7"}, {"href": "/bbs/thread/52b90362a589cd1f/69738576-1.html", "topic": "\r\n\u94b1\u4ea4\u4e86\u8fd8\u6ca1\u7ed9\u63d0\u8f66            ", "author": ["//i.autohome.com.cn/65524467", "lll8034"], "create_at": "2017-12-26", "reply_count": "9"}, {"href": "/bbs/thread/3eadf96d5992ed67/69742075-1.html", "topic": "\r\n22\u53f7\u63d0\u7684\u8f66\uff0c\u5f00\u4e86\u53d1\u7968\uff0c\u8bf7\u95ee\u8d2d\u7f6e\u7a0e\u8fd8\u662f75\u6298\u5417            ", "author": ["//i.autohome.com.cn/35286229", "247233710"], "create_at": "2017-12-27", "reply_count": "4"}, {"href": "/bbs/thread/31f8bedf9344e9f4/69643165-1.html", "topic": "\r\n\u8d37\u6b3e\u843d\u573017.7\u8d35\u5427\uff1f            ", "author": ["//i.autohome.com.cn/64416808", "\u597d\u5947\u5fc3\u7684\u6298\u8033"], "create_at": "2017-12-23", "reply_count": "42"}, {"href": "/bbs/thread/ac72ff530d0bbeae/69716599-1.html", "topic": "\r\n\u5e95\u76d8\u6cb9\u7ba1\u9644\u8fd1\u4e00\u8840\uff0c\u600e\u4e48\u529e            ", "author": ["//i.autohome.com.cn/38597084", "\u6211\u8d70\u8def\u4e0d\u770b\u8def"], "create_at": "2017-12-26", "reply_count": "5"}, {"href": "/bbs/thread/e3cb4c2a4551ee23/69741812-1.html", "topic": "\r\n\u5927\u795e\u4eec\u8bf7\u8fdb\uff01            ", "author": ["//i.autohome.com.cn/36984742", "\u8428\u74e6\u8fea\u5361\u666e"], "create_at": "2017-12-27", "reply_count": "2"}, {"href": "/bbs/thread/de336e1ff5c3924d/69550651-1.html", "topic": "\r\n\u6c19\u6c14\u706f\uff0c\u548cLED\u90a3\u4e2a\u597d\uff0c\u6709\u6ca1\u6709\u5b89\u88c5\u8fc7\u7684\uff0c\u5e2e\u652f\u62db\uff0c\u8c22\u8c22\u5927\u5bb6            ", "author": ["//i.autohome.com.cn/11690503", "\u4e1c\u80dc\u5c0f\u7530\u6b4c"], "create_at": "2017-12-20", "reply_count": "51"}, {"href": "/bbs/thread/c52f198c638d1b90/69718289-1.html", "topic": "\r\n\u601d\u57df\u6392\u6c14\u7ba1\u600e\u4e48\u6539\uff0c\u5728\u7ebf\u7b49            ", "author": ["//i.autohome.com.cn/59618875", "\u5c0f\u66141"], "create_at": "2017-12-26", "reply_count": "3"}, {"href": "/bbs/thread/72d7ddb6beb0a102/69709593-1.html", "topic": "\r\n\u601d\u57df\u52a0\u88c5\u91ce\u9a6c\u706f\u95ee\u9898            ", "author": ["//i.autohome.com.cn/29054239", "\u4eba\u58f0\u5927\u5927"], "create_at": "2017-12-26", "reply_count": "11"}, {"href": "/bbs/thread/24c897d7bb23ab58/69737243-1.html", "topic": "\r\n\u6211\u7684\u4e5d\u4ee3            ", "author": ["//i.autohome.com.cn/9635446", "Jeff1029"], "create_at": "2017-12-26", "reply_count": "3"}, {"href": "/bbs/thread/608429b86004b696/67458719-1.html", "topic": "\r\n\u6709\u6c5f\u95e8\u7684\u8f66\u4e3b\u5417\uff1f            ", "author": ["//i.autohome.com.cn/37354483", "\u5f53\u8eab\u8fb9\u7684\u4e00\u5207\u5982\u98ce"], "create_at": "2017-10-12", "reply_count": "3"}, {"href": "/bbs/thread/a3bb642bd15cc363/69741043-1.html", "topic": "\r\n\u9965\u6e34\u8425\u9500            ", "author": ["//i.autohome.com.cn/54442816", "ABC\u4e94\u54e5"], "create_at": "2017-12-27", "reply_count": "0"}, {"href": "/bbs/thread/edbe3d16e63dd6c1/69678171-1.html", "topic": "\r\n\u5220\u4e0d\u6389\u8d34\u53ea\u80fd\u8fd9\u6837\u4e86            ", "author": ["//i.autohome.com.cn/33462704", "\u662f\u9a9a\u95ea\u4e86\u8170"], "create_at": "2017-12-25", "reply_count": "11"}, {"href": "/bbs/thread/9bb209af315b8c8f/69736148-1.html", "topic": "\r\n\u4ea4\u901a\u4e8b\u6545\u5168\u8d23\u65b9\u9700\u8981\u989d\u5916\u8d54\u507f\u5bf9\u65b9\u4fdd\u9669\u4ee5\u5916\u7684\u9879\u76ee\u5417\uff1f\u6bd4\u5982\u8f6e\u80ce\u3002            ", "author": ["//i.autohome.com.cn/28181933", "cherrychilli"], "create_at": "2017-12-26", "reply_count": "6"}, {"href": "/bbs/thread/4f27984c69810e06/69730953-1.html", "topic": "\r\n\u4e24\u4e2a\u5c0f\u95ee\u9898\uff0c\u61c2\u7684\u89e3\u7b54\u4e0b            ", "author": ["//i.autohome.com.cn/54030020", "\u626b\u4f60\u7075\u771f\u7ec7"], "create_at": "2017-12-26", "reply_count": "3"}, {"href": "/bbs/thread/050980eeec3b654a/67428145-1.html", "topic": "\r\n\u6e56\u5357\u5cb3\u9633\u5341\u4ee3\u601d\u57df            ", "author": ["//i.autohome.com.cn/38747574", "wx1688888"], "create_at": "2017-10-11", "reply_count": "4"}, {"href": "/bbs/thread/4f3dedd0421b945a/69731869-1.html", "topic": "\r\n\u660e\u5929\u53bb\u6210\u90fd\u8ba2\u601d\u57df\u624b\u8c6a\u670b\u53cb\u4eec\u7ed9\u70b9\u5efa\u8bae            ", "author": ["//i.autohome.com.cn/38117143", "\u4f60\u5bb6\u9644\u8fd1"], "create_at": "2017-12-26", "reply_count": "6"}, {"href": "/bbs/thread/92d677d82bb32b34/69701271-1.html", "topic": "\r\n\u8001\u53f8\u673a\u5e2e\u6211\u770b\u770b            ", "author": ["//i.autohome.com.cn/24596040", "zj1079702333"], "create_at": "2017-12-25", "reply_count": "14"}, {"href": "/bbs/thread/c77f5c820ab21a06/69736003-1.html", "topic": "\r\n\u8001\u53f8\u673a\u8fdb\u6765\u770b\u770b\uff0c\u840c\u65b0\u4e0d\u8ba4\u8bc6\u4ec0\u4e48\u8f66\uff0c\u662f\u601d\u57df\u5417            ", "author": ["//i.autohome.com.cn/60069701", "BiuBiuBiu______"], "create_at": "2017-12-26", "reply_count": "4"}, {"href": "/bbs/thread/975ecf80214bc7e2/69575569-1.html", "topic": "\r\n\u51famagicpro\u5916\u6302\uff0c\u63d0\u5347\u660e\u663e\uff0c\u52a8\u529b\u9b54\u6cd5\u4ece\u6b64\u5f00\u542f\uff0c\u7248\u4e3b\u7559\u60c5            ", "author": ["//i.autohome.com.cn/6272090", "ysxx2013"], "create_at": "2017-12-21", "reply_count": "17"}, {"href": "/bbs/thread/82e502a6bca61b51/69638629-1.html", "topic": "\r\n\u5341\u4ee3\u601d\u57df \u4e00\u5e74\u4e86 \u4e24\u4e07\u516c\u91cc \u60f3\u6362\u65b0\u65e5\u77f30w20\u673a\u6cb9 \u8c01\u6709\u6b63\u54c1\u6e20\u9053\u554a            ", "author": ["//i.autohome.com.cn/65269699", "\u560e\u560e\u5c31\u662f\u58f3"], "create_at": "2017-12-23", "reply_count": "9"}, {"href": "/bbs/thread/3fd0e4c355a42fef/69730763-1.html", "topic": "\r\n\u4fee\u4fee\u591a\u5c11\u94b1\uff1f            ", "author": ["//i.autohome.com.cn/37811984", "\u6c5f\u6c5f430"], "create_at": "2017-12-26", "reply_count": "9"}, {"href": "/bbs/thread/6dba62a816536a77/65115042-1.html", "topic": "\r\n\u6e56\u5357\u6c38\u5dde\u7684\u4e1c\u672c4S\u5e97\uff0c\u601d\u57df1.5T\u81ea\u8c6a\u5c45\u7136\u898116.6\u4e07\u843d\u5730\uff0c\u725b\u903c            ", "author": ["//i.autohome.com.cn/16257562", "\u5434\u5b87\u7fd41993"], "create_at": "2017-07-25", "reply_count": "44"}, {"href": "/bbs/thread/56dc2ccb284a625a/69715996-1.html", "topic": "\r\n\u5341\u4ee3\u601d\u57df\u6d4e\u5357\u8f66\u53cb\u7fa4\u6709\u5417            ", "author": ["//i.autohome.com.cn/63607853", "\u541b\u5b50\u6c34\u5e72"], "create_at": "2017-12-26", "reply_count": "5"}, {"href": "/bbs/thread/6a1059b490ee778c/68528191-1.html", "topic": "\r\n\u60f3\u95ee\u4e00\u4e0b\u88c5\u4e86magicPro\u540e\u6709\u4ec0\u4e48\u6ce8\u610f\u4e8b\u9879\u5417            ", "author": ["//i.autohome.com.cn/61409336", "wuguanfengyue1"], "create_at": "2017-11-16", "reply_count": "11"}, {"href": "/bbs/thread/7d9978b058423e15/69619124-1.html", "topic": "\r\n\u7ea0\u7ed3\u624b\u52a8\u81ea\u52a8            ", "author": ["//i.autohome.com.cn/36239096", "\u795e\u8f66\u662f\u8c01\u7684"], "create_at": "2017-12-22", "reply_count": "48"}, {"href": "/bbs/thread/983291f461fe4cfc/69687226-1.html", "topic": "\r\n\u7eed\u4fdd\u80fd\u4e0d\u57284\u513f\u5b50\u90a3\u91cc\u4e70\u5417            ", "author": ["//i.autohome.com.cn/55227797", "a786751381"], "create_at": "2017-12-25", "reply_count": "5"}, {"href": "/bbs/thread/fb266d6bc1542537/69731675-1.html", "topic": "\r\n\u8fd9\u4e2a\u5f00\u542f\u4e86\u662f\u4e0d\u662f\u79bb\u5f00\u8f66\u540e\u5c31\u81ea\u5df1\u4e0a\u9501\u4e86\uff1f\uff1f            ", "author": ["//i.autohome.com.cn/56950704", "\u563f\u4e36\u7537\u5b69"], "create_at": "2017-12-26", "reply_count": "5"}, {"href": "/bbs/thread/9698d8d1fb16de9b/69731583-1.html", "topic": "\r\n\u7535\u74f6\u6ca1\u7535\u95ee\u9898            ", "author": ["//i.autohome.com.cn/61975601", "a413619919"], "create_at": "2017-12-26", "reply_count": "12"}, {"href": "/bbs/thread/f85b27490d070693/69728749-1.html", "topic": "\r\n\u8001\u53f8\u673a\u8fdb\u6765\u770b\u770b            ", "author": ["//i.autohome.com.cn/53559686", "\u5e1d\u8c6a\u5a31\u4e50\u57ce"], "create_at": "2017-12-26", "reply_count": "8"}, {"href": "/bbs/thread/334624be57e7d746/69730371-1.html", "topic": "\r\n\u81ea\u52a8\u542f\u505c\u4e0d\u80fd\u7528\u4e86            ", "author": ["//i.autohome.com.cn/5728478", "\u4e00\u751f\u7684\u631a\u7231"], "create_at": "2017-12-26", "reply_count": "4"}, {"href": "/bbs/thread/f7258ed662e3bc0e/69731854-1.html", "topic": "\r\n\u8bf7\u95ee\u5404\u4f4d            ", "author": ["//i.autohome.com.cn/61838513", "\u604b\u4eba\u672a\u6ee1\u4e00\u751f\u5e73\u5b89"], "create_at": "2017-12-26", "reply_count": "3"}, {"href": "/bbs/thread/3e88f51c01f2c51f/69730393-1.html", "topic": "\r\n\u5341\u4ee3\u601d\u57df\u6539\u88c5\u95ee\u9898\uff01            ", "author": ["//i.autohome.com.cn/65275758", "Porshe\u4e36"], "create_at": "2017-12-26", "reply_count": "5"}, {"href": "/bbs/thread/4fbe090d629172cb/66866212-1.html", "topic": "\r\n\u559c\u6b22\u4f60\u7684\u591a\u53d8\uff0c\u4e0d\u540c\u89d2\u5ea6\u4e0b\u4f1a\u6709\u4e0d\u4e00\u6837\u7684\u5b83            ", "author": ["//i.autohome.com.cn/53828961", "CherylBurke"], "create_at": "2017-09-22", "reply_count": "4"}, {"href": "/bbs/thread/8d3666f88361542f/69734982-1.html", "topic": "\r\n\u65e0\u94a5\u5319\u8fdb\u5165\u5931\u7075            ", "author": ["//i.autohome.com.cn/36212146", "8339121"], "create_at": "2017-12-26", "reply_count": "3"}, {"href": "/bbs/thread/58093c60dc020150/69327152-1.html", "topic": "\r\n\u5e7f\u4e1c\u4e2d\u5c71\u6709\u6ca1\u6709\u4e0d\u8981\u7684\u601d\u57df\u8ba2\u5355            ", "author": ["//i.autohome.com.cn/58808535", "\u5c0f\u660e\u540c\u5b66ai"], "create_at": "2017-12-12", "reply_count": "19"}, {"href": "/bbs/thread/677897ff632b2386/69635942-1.html", "topic": "\r\n\u4f19\u4f34\u4eec\u4f60\u4eec\u7684\u5c0f\u601d\u57df\u90fd\u7528\u4ec0\u4e48\u724c\u5b50\u7684\u884c\u8f66\u8bb0\u5f55\u4eea\uff1f            ", "author": ["//i.autohome.com.cn/56287599", "\u7ba1\u6c61\u6c61"], "create_at": "2017-12-23", "reply_count": "8"}, {"href": "/bbs/thread/fb9620ed50e42d63/69734416-1.html", "topic": "\r\n\u5173\u4e8e\u52a0\u8ba4\u8bc1\u7684\u95ee\u9898            ", "author": ["//i.autohome.com.cn/11452415", "\u5c0f\u8fc8\u5c0f\u9ea6"], "create_at": "2017-12-26", "reply_count": "1"}, {"href": "/bbs/thread/995f86223a699751/69707137-1.html", "topic": "\r\n\u521a\u624d\u8def\u4e0a\u770b\u5230\u4e00\u8f86\u7f8e\u7248\u601d\u57df            ", "author": ["//i.autohome.com.cn/65436268", "\u6700\u540e\u7684\u51b0\u5ddd"], "create_at": "2017-12-25", "reply_count": "10"}, {"href": "/bbs/thread/035bb19a83e07cd4/69699819-1.html", "topic": "\r\n\u81ea\u52a8\u7a7a\u8c03            ", "author": ["//i.autohome.com.cn/28875731", "\u67ab\u7b2b"], "create_at": "2017-12-25", "reply_count": "8"}, {"href": "/bbs/thread/679a5bb02663c19b/69462684-1.html", "topic": "\r\n\u53a6\u95e8\u4eca\u5929\u53bb\u54a8\u8be2\u4e86\u601d\u57df\u4ef7\u683c\u987a\u4fbf\u8bd5\u9a7e\u4e86\u4e0b            ", "author": ["//i.autohome.com.cn/52272854", "\u6c38\u5c81\u98d8\u96f6\u4e45\u4e45"], "create_at": "2017-12-17", "reply_count": "13"}, {"href": "/bbs/thread/d6f078f300e88b1c/69719421-1.html", "topic": "\r\n9\u4ee3\u601d\u57df\u6362\u673a\u6cb9            ", "author": ["//i.autohome.com.cn/9908904", "lllhhjxjm"], "create_at": "2017-12-26", "reply_count": "9"}, {"href": "/bbs/thread/4c1bb34089793553/69716461-1.html", "topic": "\r\n9\u4ee3\u601d\u57df\u80fd\u4e0d\u80fd\u88c510\u4ee3\u601d\u57df\u7684\u65b9\u5411\u76d8\uff01\uff01\uff01\uff1f            ", "author": ["//i.autohome.com.cn/8055826", "gui1118"], "create_at": "2017-12-26", "reply_count": "6"}, {"href": "/bbs/thread/1db2700fb8d4533d/69724815-1.html", "topic": "\r\n\u5404\u4f4d\u8001\u54e5\u5e2e\u5fd9\u770b\u4e0b\u673a\u8231\u91cc\u8fd9\u5757\u6d77\u7ef5\u662f\u505a\u4ec0\u4e48\u7528\u7684\uff0c\u4e00\u4e07\u4e09\u5343\u516c\u91cc\u70c2\u4e86            ", "author": ["//i.autohome.com.cn/25436545", "y____5"], "create_at": "2017-12-26", "reply_count": "6"}, {"href": "/bbs/thread/96387921ac3d25f8/69689395-1.html", "topic": "\r\n\u60f3\u63d0\u9ed1\u8272 \u5927\u5bb6\u6709\u6ca1\u6709\u63d0\u9ed1\u8272\u7684 \u540a\u5927\u7684\u53d1\u4e2a\u56fe\u7247            ", "author": ["//i.autohome.com.cn/23823268", "720999"], "create_at": "2017-12-25", "reply_count": "17"}, {"href": "/bbs/thread/9487f92cc3abc2d8/67324770-1.html", "topic": "\r\n10\u5468\u5e74\u5c0f\u60c5\u4eba\u6362\u978b\u7a7f            ", "author": ["//i.autohome.com.cn/8055102", "\u6b27\u9633\u6e05\u534e"], "create_at": "2017-10-08", "reply_count": "1"}, {"href": "/bbs/thread/a7e16c282544c811/69717004-1.html", "topic": "\r\n\u5e2e\u5fd9\u731c\u4e2a\u8f66\uff0c\u8c22\u8c22            ", "author": ["//i.autohome.com.cn/13696207", "\ufffd\ufffd\ufffd\ufffd\ufffdU\ufffd\u9c90\ufffd\ufffd\ufffd\ufffd\ufffd\ufffd_\ufffd\ufffd"], "create_at": "2017-12-26", "reply_count": "2"}, {"href": "/bbs/thread/6ece39fb39acedbe/69665559-1.html", "topic": "\r\n\u6bd5\u4e1a\u540e\u7684\u793c\u7269            ", "author": ["//i.autohome.com.cn/52953525", "\u5fc3\u52a8\u7f8e"], "create_at": "2017-12-24", "reply_count": "5"}, {"href": "/bbs/thread/d009d4ef62bccd4b/69729352-1.html", "topic": "\r\n\u601d\u57df\u7684\u7ea2\u8272\u548c\u84dd\u8272\u90fd\u662f\u91d1\u5c5e\u6f06\u5417            ", "author": ["//i.autohome.com.cn/17878843", "Dong\u5730\u74dc"], "create_at": "2017-12-26", "reply_count": "7"}, {"href": "/bbs/thread/0bcbd9be2c476e56/69707142-1.html", "topic": "\r\n\u8fd9\u662f\u4ec0\u4e48\u8f66\u578b            ", "author": ["//i.autohome.com.cn/24894284", "JakForget"], "create_at": "2017-12-25", "reply_count": "4"}, {"href": "/bbs/thread/c47595cf2da336cf/69728392-1.html", "topic": "\r\n\u6211\u8fd9\u8f66\u662f\u7ecf\u9500\u5546\u5916\u5730\u62c9\u7684            ", "author": ["//i.autohome.com.cn/25054059", "\u65e0\u540d\u4f60"], "create_at": "2017-12-26", "reply_count": "4"}, {"href": "/bbs/thread/d14c444b333917c3/69729077-1.html", "topic": "\r\n\u8001\u94c1\u4eec\uff0c\u4f60\u4eec\u4e0a\u724c\u8f66\u7ba1\u6240\u7ed9\u4e86\u51e0\u4e2a\u87ba\u4e1d\uff1f            ", "author": ["//i.autohome.com.cn/63602208", "\u79cb\u540d\u5c71\u5c0f\u5b66\u751f"], "create_at": "2017-12-26", "reply_count": "15"}, {"href": "/bbs/thread/ef8d479d511ed93b/69724071-1.html", "topic": "\r\n\u73e0\u6d77\u601d\u57df            ", "author": ["//i.autohome.com.cn/62656228", "\u73e0\u6d77\u5468\ufffd\ufffd\ufffdl"], "create_at": "2017-12-26", "reply_count": "3"}, {"href": "/bbs/thread/0b2df83f28aaa131/68358734-1.html", "topic": "\r\n\u5fb7\u9633\u5730\u533a\u6709\u6ca1\u6709\u601d\u57df\u8f66\u4e3b\u3002            ", "author": ["//i.autohome.com.cn/38827852", "\u5978\u7b11\u7684\u6211"], "create_at": "2017-11-10", "reply_count": "5"}, {"href": "/bbs/thread/da77bc2f63b305fb/69622758-1.html", "topic": "\r\n\u5e7f\u4e1c\u65368.5\u4ee3\u601d\u57df            ", "author": ["//i.autohome.com.cn/26568956", "Liuhaifengliuhaifeng"], "create_at": "2017-12-23", "reply_count": "4"}, {"href": "/bbs/thread/67815030e666e9b9/69729748-1.html", "topic": "\r\n\u6709\u6ca1\u6709\u4eba\u88c5\u4e00\u952e\u964d\u73bb\u7483\u7684            ", "author": ["//i.autohome.com.cn/10681019", "Chrishuai"], "create_at": "2017-12-26", "reply_count": "7"}, {"href": "/bbs/thread/89d80107243e8bc7/69660440-1.html", "topic": "\r\n\u5220\u5e16...            ", "author": ["//i.autohome.com.cn/30715369", "\u5411\u531701"], "create_at": "2017-12-24", "reply_count": "3"}, {"href": "/bbs/thread/0af89ae21526b749/69463108-1.html", "topic": "\r\n\u51fa\u63a2\u8def\u6cfd\u6d41\u5149\u8f6c\u5411\u603b\u6210\uff01            ", "author": ["//i.autohome.com.cn/27029860", "hb747371673"], "create_at": "2017-12-17", "reply_count": "10"}, {"href": "/bbs/thread/4476507456c7ff27/69656765-1.html", "topic": "\r\n\u751f\u6c14  \u90c1\u95f7 \u5230\u5e95\u503c\u4e0d\u503c\u5462            ", "author": ["//i.autohome.com.cn/55845016", "51999999"], "create_at": "2017-12-24", "reply_count": "7"}, {"href": "/bbs/thread/d2374dc2f4c8438b/68455014-1.html", "topic": "\r\n\u5341\u4ee3\u601d\u57df\u7684\u80ce\u538b\u76d1\u6d4b\u600e\u4e48\u4f7f\u7528\u554a\uff0c\u80fd\u4e0d\u80fd\u4ece\u4eea\u8868\u76d8\u770b\u51fa\u80ce\u538b\u538b\u529b\u538b\u503c            ", "author": ["//i.autohome.com.cn/58909705", "chenhao147369"], "create_at": "2017-11-14", "reply_count": "14"}, {"href": "/bbs/thread/80cc2e1e294254fb/69690231-1.html", "topic": "\r\n\u4e70\u4e86\u4e00\u53f0\u5047\u601d\u57df            ", "author": ["//i.autohome.com.cn/22455963", "\u87ba\u6d69"], "create_at": "2017-12-25", "reply_count": "27"}, {"href": "/bbs/thread/559c20e08636c434/69707816-1.html", "topic": "\r\n\u672c\u7530\u73b0\u5728\u90fd\u662f\u5730\u7403\u68a6\u53d1\u52a8\u673a\u4e86\u5417\uff1f            ", "author": ["//i.autohome.com.cn/17679560", "\u65e5\u7cfb\u5fb7\u7cfb\u6700\u7231"], "create_at": "2017-12-25", "reply_count": "26"}, {"href": "/bbs/thread/c7c6f4b85b82a785/69699335-1.html", "topic": "\r\n\u6c42\u95ee\u5927\u795e\u4eec\u6539\u6392\u6c14\u95ee\u9898            ", "author": ["//i.autohome.com.cn/38316781", "6811770"], "create_at": "2017-12-25", "reply_count": "8"}, {"href": "/bbs/thread/22b21f645f7683d6/65393614-1.html", "topic": "\r\n\u5bfb\u627e\u5341\u4ee3\u601d\u57df\u540c\u6837\u5c3e\u7ffc\u7684\u4f60\uff0c\u897f\u5b89\u7684\u5144\u5f1f\uff01\uff01            ", "author": ["//i.autohome.com.cn/5226476", "\u556a\u556a\u5c0f\u4e94\u5b50"], "create_at": "2017-08-04", "reply_count": "35"}, {"href": "/bbs/thread/7b450fc235d29c11/69657116-1.html", "topic": "\r\n\u5723\u8bde\u8282\u6536\u5230\u7684\u601d\u57df\u9970\u54c1\u793c\u7269\uff01----\u95f7\u9a9a\u7684\u793c\u7269            ", "author": ["//i.autohome.com.cn/65325505", "\u5c71\u5be8\u8dd1\u8f662018"], "create_at": "2017-12-24", "reply_count": "18"}, {"href": "/bbs/thread/e472d5b31f02c57d/69727294-1.html", "topic": "\r\n\u5de5\u5177\u8fd9\u4e2a\u7f3a\u4e86\u4e2a\u4ec0\u4e48\uff1f            ", "author": ["//i.autohome.com.cn/57206108", "\u522b\u81f4\u7684\u4f9d\u8d56abc"], "create_at": "2017-12-26", "reply_count": "8"}, {"href": "/bbs/thread/9f1725ef0fa41716/69694789-1.html", "topic": "\r\n\u4e24\u4e2a\u591a\u6708\u7b2c\u4e00\u6b214s\u5e97\u7ef4\u4fee            ", "author": ["//i.autohome.com.cn/53553570", "ZoomLeung"], "create_at": "2017-12-25", "reply_count": "11"}, {"href": "/bbs/thread/5f97f96772a8a369/69672841-1.html", "topic": "\r\n\u767d\u8272\u8f66\u6f06\u9762\u6709\u5f88\u591a\u9ec4\u8272\u5c0f\u94c1\u9508            ", "author": ["//i.autohome.com.cn/39073393", "\u77f3\u4f5b55555"], "create_at": "2017-12-24", "reply_count": "9"}, {"href": "/bbs/thread/0f76fa7870c1c9dc/67471166-1.html", "topic": "\r\n111111111111111111            ", "author": ["//i.autohome.com.cn/21581719", "\u8549sir"], "create_at": "2017-10-12", "reply_count": "288"}, {"href": "/bbs/thread/8d8eaee11a91107b/69161212-1.html", "topic": "\r\n\u8bdd\u8bf4\u6211\u5728\u6dd8\u5b9d\u4e0a\u770b\u52301.0T 180\u7684\u8d34\u6807\u4e86\uff0c            ", "author": ["//i.autohome.com.cn/31438476", "\u5c0f\u602a\u517d\u73b0\u5728\u4e0d\u60f3\u8d70"], "create_at": "2017-12-07", "reply_count": "13"}, {"href": "/bbs/thread/d068312693325345/69544907-1.html", "topic": "\r\n\u6012\u63d0\u601d\u57df\uff0c\u53ea\u4e3a\u5151\u73b0\u5f53\u521d\u5439\u8fc7\u7684\u725b\u903c            ", "author": ["//i.autohome.com.cn/26519760", "\u65e0\u5957\u4e0d\u505a"], "create_at": "2017-12-20", "reply_count": "50"}, {"href": "/bbs/thread/a1bcc091275ead8b/69717885-1.html", "topic": "\r\n\u6709\u51fa8.5\u624b\u52a8\u7684\u5417\uff1f            ", "author": ["//i.autohome.com.cn/8699550", "\u5a5a\u793c\u4e3b\u6301\u6587\u607a"], "create_at": "2017-12-26", "reply_count": "3"}, {"href": "/bbs/thread/33cf3840dce4f705/69434183-1.html", "topic": "\r\n\u601d\u57df\u6709\u6ca1\u6709\u63d01.0T\u7684\uff01            ", "author": ["//i.autohome.com.cn/20907069", "\u626f\u6de1\u7684\u9a9a\u5e74"], "create_at": "2017-12-16", "reply_count": "16"}, {"href": "/bbs/thread/51cf25267d5957b3/69705550-1.html", "topic": "\r\n\u6447\u53f7\u771f\u8d39\u52b2            ", "author": ["//i.autohome.com.cn/5903995", "\u5929\u5927\u5317\u6d0b"], "create_at": "2017-12-25", "reply_count": "7"}, {"href": "/bbs/thread/1009f10fc77fe3c8/69726394-1.html", "topic": "\r\n\u5927\u5bb6\u5e2e\u6211\u770b\u4e0b\u8fd9\u4e2a\u4ef7\u683c\uff01            ", "author": ["//i.autohome.com.cn/25070003", "\u6960\u795e\u5a31\u4e50"], "create_at": "2017-12-26", "reply_count": "5"}, {"href": "/bbs/thread/41bfca975cf65c82/69135854-1.html", "topic": "\r\n\u5173\u4e8e\u6cb9\u8017\uff0c\u5c0f\u5f1f\u521a\u63d0\u8f66\u81ea\u8c6a\u3002\u8001\u53f8\u673a\u9ebb\u70e6\u770b\u4e0b\u3002            ", "author": ["//i.autohome.com.cn/27660491", "1004100329liu"], "create_at": "2017-12-06", "reply_count": "36"}, {"href": "/bbs/thread/2148e0289e9a9fdc/69728124-1.html", "topic": "\r\n\u81ea\u8c6a \u6709\u73b0\u8f66            ", "author": ["//i.autohome.com.cn/65129311", "\u90b1\u6eaa\u6c34"], "create_at": "2017-12-26", "reply_count": "0"}, {"href": "/bbs/thread/47b9c70289ff4cd5/69689333-1.html", "topic": "\r\n\u6709\u539f\u5382\u540e\u89c6\u955c\u6298\u53e0\u5417\uff1f            ", "author": ["//i.autohome.com.cn/11235587", "\u58a8\u7fbd\u98ce\u534e"], "create_at": "2017-12-25", "reply_count": "8"}, {"href": "/bbs/thread/786d520d02ed366b/64505391-1.html", "topic": "\r\n\u97f3\u54cd\u4e0d\u54cd\u51fa\u73b0\u201c\u97f3\u9891\u5c06\u81ea\u52a8\u9759\u97f3 \u4ee5\u6700\u5c0f\u5316\u5f53\u524d\u6d88\u8017\u201d            ", "author": ["//i.autohome.com.cn/29630786", "\u5382\u54e5\u513f"], "create_at": "2017-07-03", "reply_count": "22"}, {"href": "/bbs/thread/eb8c0a4ac50cb2ca/69725168-1.html", "topic": "\r\n\u8ba2\u8f66\u5408\u540c\u7b7e\u4e86\u8fd8\u80fd\u5728\u8c08\u4ef7\u94b1\u5417            ", "author": ["//i.autohome.com.cn/65109409", "\u5443\u5443\u5443\u5443d"], "create_at": "2017-12-26", "reply_count": "7"}, {"href": "/bbs/thread/ae176ecde803a68d/69716111-1.html", "topic": "\r\n\u601d\u57df\u5c0a\u8d35\u6709\u771f\u76ae\u5ea7\u6905\u6ca1\uff0c\u6c42\u544a\u8bc9            ", "author": ["//i.autohome.com.cn/16988934", "\u613f\u5f97\u6211\u4e00\u4eba\u5b64\u72ec\u7ec8\u8001"], "create_at": "2017-12-26", "reply_count": "10"}, {"href": "/bbs/thread/5e7efeebda9c3bc1/69613150-1.html", "topic": "\r\n\u540e\u8f66\u80ce\u5185\u4fa7\u624e\u4e86\u4e2a\u9489\u5b50\uff0c\u6162\u6492\u6c14            ", "author": ["//i.autohome.com.cn/40026296", "\u6211\u7231\u5c0f\u65af\u601d\u601d"], "create_at": "2017-12-22", "reply_count": "14"}, {"href": "/bbs/thread/05600b93aef2cc58/69716270-1.html", "topic": "\r\n\u95ee\u5927\u795e\u4e2a\u4e2d\u63a7\u5c4f\u7684\u95ee\u9898            ", "author": ["//i.autohome.com.cn/39544620", "wxky007"], "create_at": "2017-12-26", "reply_count": "3"}, {"href": "/bbs/thread/c4d216339c548e84/69700707-1.html", "topic": "\r\n\u591a\u4e45\u53ef\u4ee5\u63d0\ufffd\ufffd?            ", "author": ["//i.autohome.com.cn/11579372", "martinchiang"], "create_at": "2017-12-25", "reply_count": "4"}, {"href": "/bbs/thread/1ece19dbeea21bb7/69678400-1.html", "topic": "\r\n\u672c\u4eba\u521a\u63d0\u8f66\u601d\u57df            ", "author": ["//i.autohome.com.cn/59176504", "\u519c\u6c11\u54e5\u963f\u6c64"], "create_at": "2017-12-25", "reply_count": "4"}, {"href": "/bbs/thread/42779a9a8b017fe9/69722523-1.html", "topic": "\r\n\u5341\u4ee3\u601d\u57df\u5173\u4e8e\u673a\u6cb9            ", "author": ["//i.autohome.com.cn/38502239", "\u8c46\u8c46\u65af\u57fa"], "create_at": "2017-12-26", "reply_count": "9"}, {"href": "/bbs/thread/9090550b8928055b/69715207-1.html", "topic": "\r\n\u4e2d\u67aa\u4e86\uff0c\u540e\u9762\u88ab\u4e00\u5356\u65e9\u9910\u4e09\u8f6e\u8f66\u52a0\u585e\u4e86            ", "author": ["//i.autohome.com.cn/53961402", "\u6e05\u9192\u65f6\u597d\u7d2f"], "create_at": "2017-12-26", "reply_count": "17"}, {"href": "/bbs/thread/9a74a9ec2e50a483/69713020-1.html", "topic": "\r\n\u8bf7\u6559\u8001\u53f8\u673a\uff01            ", "author": ["//i.autohome.com.cn/36610620", "zxh\u6295\u6295123"], "create_at": "2017-12-26", "reply_count": "6"}, {"href": "/bbs/thread/7db80c274a15cc60/69712102-1.html", "topic": "\r\n\u6253\u7b97\u4e701.5\u4e00\u8c6a\uff0c\u52a0\u4ef7\u80fd\u8981\u6c42\u52a0\u4ec0\u4e48\u4e1c\u897f\uff1f            ", "author": ["//i.autohome.com.cn/65437401", "\u5416Q\u54e5"], "create_at": "2017-12-26", "reply_count": "15"}, {"href": "/bbs/thread/28aa54f871ccb860/69718756-1.html", "topic": "\r\n\u5947\u602a\u4e86\uff0c\u8fd9\u8f66            ", "author": ["//i.autohome.com.cn/60372114", "\u767d\u5148\u751f\u767d"], "create_at": "2017-12-26", "reply_count": "10"}, {"href": "/bbs/thread/af97cfcad670016c/69715820-1.html", "topic": "\r\n\u795d\u5927\u5bb6\u90fd\u5e73\u5b89\u5f00\u8f66            ", "author": ["//i.autohome.com.cn/37409487", "\u5168\u90fd\u884c"], "create_at": "2017-12-26", "reply_count": "9"}, {"href": "/bbs/thread/1e77c3c83c5604bd/67474693-1.html", "topic": "\r\n\u676d\u5dde\u6ee8\u6c5f            ", "author": ["//i.autohome.com.cn/58030025", "\u68a6\u957f\u591c\u8fd8\u591a"], "create_at": "2017-10-12", "reply_count": "2"}, {"href": "/bbs/thread/b8503f1636d33bfc/69716930-1.html", "topic": "\r\n\u8fd9\u4e2a\u95ee\u9898\u662f\u4ec0\u4e48            ", "author": ["//i.autohome.com.cn/23778479", "\u597d\u4eba\u597d\u4e8b\u591a"], "create_at": "2017-12-26", "reply_count": "4"}]