[{"href": "/bbs/thread/abb11332d7bed230/66540786-1.html", "topic": "\r\n\u94f6\u884c\u8d37\u6b3e\u4e70\u7684\u8f66\u9700\u8981\u62bc\u4ec0\u4e48\u7ed9\u4ed6\uff1f            ", "author": ["//i.autohome.com.cn/54532799", "\u53eb\u6211\u5973\u738b\u5927\u5927\u5927\u4eba"], "create_at": "2017-09-11", "reply_count": "5"}, {"href": "/bbs/thread/efc168e555f01946/66540539-1.html", "topic": "\r\n\u660e\u5929\u63d0\u8f66\u6709\u4ec0\u4e48\u9700\u8981\u6ce8\u610f\u7684\u5417\uff1f            ", "author": ["//i.autohome.com.cn/52814456", "125478_2017"], "create_at": "2017-09-11", "reply_count": "6"}, {"href": "/bbs/thread/6417732be4d2ec01/66528636-1.html", "topic": "\r\n\u8fd9\u4e1c\u897f\u6709\u6ca1\u5fc5\u8981\u4e70            ", "author": ["//i.autohome.com.cn/54267956", "\u955c\u540e\u4eba"], "create_at": "2017-09-11", "reply_count": "17"}, {"href": "/bbs/thread/472b7df8f313ab66/66540153-1.html", "topic": "\r\n\u672c\u7530\u601d\u57df            ", "author": ["//i.autohome.com.cn/40991663", "\u5c0f\u602a\u517dEric\u4e36"], "create_at": "2017-09-11", "reply_count": "3"}, {"href": "/bbs/thread/09575bfc68392de3/66488129-1.html", "topic": "\r\n\u5341\u4ee3\u601d\u57df\uff0c\u53f3\u4fa7\u5b89\u5168\u5e26\u9644\u8fd1\u7c7b\u4f3c\u5f39\u7c27\u58f0\u97f3\u7684\u5f02\u54cd\uff01            ", "author": ["//i.autohome.com.cn/39166228", "\u627f\u8f7d\u7075\u9b42\u7684\u5fc3"], "create_at": "2017-09-10", "reply_count": "16"}, {"href": "/bbs/thread/9cbc15bd5a71cf39/66529167-1.html", "topic": "\r\n\u65b0\u8f66\u73b0\u5728\u53ef\u4ee5\u529e\u51e0\u5f20\u4e34\u65f6\u724c\uff1f\u4e00\u5f20\u53ef\u4ee5\u7528\u591a\u4e45\uff1f\uff1f            ", "author": ["//i.autohome.com.cn/30219264", "\u6770\u5c115173"], "create_at": "2017-09-11", "reply_count": "6"}, {"href": "/bbs/thread/673e84c3209e057a/66539119-1.html", "topic": "\r\n\u53ef\u4ee5\u804a\u4e00\u70b9\u5173\u4e8e\u65b0\u96f7\u51cc185T\u64cd\u63a7\u6027\u7684\u611f\u53d7            ", "author": ["//i.autohome.com.cn/56345690", "\u51cc\u9999c5"], "create_at": "2017-09-11", "reply_count": "2"}, {"href": "/bbs/thread/29a5c6cae04b6082/66529340-1.html", "topic": "\r\n\u5e7f\u5dde\u4eac\u60526\u6708\u5b9a\u94f6\u8272\u7684\u63d0\u8f66\u4e86\u5417\uff1f            ", "author": ["//i.autohome.com.cn/14831057", "\u5468\ufffd\ufffd\u901b\u901b"], "create_at": "2017-09-11", "reply_count": "5"}, {"href": "/bbs/thread/f8ee23197c1c60bb/66493419-1.html", "topic": "\r\n\u6539\u88c5\u540e\u7684\u524d\u6760\u540e\u6760\u653e\u54ea\u91cc\u50a8\u5b58\u597d\u5462            ", "author": ["//i.autohome.com.cn/21032099", "flycoldbat"], "create_at": "2017-09-10", "reply_count": "17"}, {"href": "/bbs/thread/36d4f9e802c03ca6/66526077-1.html", "topic": "\r\n\u5e95\u76d8\u88c5\u7532\u5bf9\u5e95\u76d8\u9694\u97f3\u6709\u6548\u679c\u554a            ", "author": ["//i.autohome.com.cn/27869286", "\u4e0d\u80fd\u767d\u6d3b\u4e00\u8f88\u5b50"], "create_at": "2017-09-11", "reply_count": "8"}, {"href": "/bbs/thread/78c174559ca26844/66514635-1.html", "topic": "\r\n\u672c\u4eba\u5c0f\u767d\u8bf7\u6559\u5927\u795e\u4eec            ", "author": ["//i.autohome.com.cn/56131541", "as118\u5f20\u8302\u7fa4"], "create_at": "2017-09-10", "reply_count": "4"}, {"href": "/bbs/thread/eb0a560fe2588380/66522514-1.html", "topic": "\r\n\u5f02\u5730\u63d0\u8f66\u9ebb\u70e6\u5417\uff0c\u51c6\u5907\u8ba2\u601d\u57df\u4e86\u3002\u6709\u88ab\u5751\u4e48\uff0c\u5404\u4f4d\u5927\u795e            ", "author": ["//i.autohome.com.cn/38708836", "\u4ece\u6b64\u65e0\u5fc3\u7231\u826f\u591c_"], "create_at": "2017-09-11", "reply_count": "12"}, {"href": "/bbs/thread/54ff37cf830ac05a/66537135-1.html", "topic": "\r\n\u5341\u4ee3\u601d\u57df\u5c0a\u8ba2\u8f66            ", "author": ["//i.autohome.com.cn/57369755", "258\u9ed1\u6697\u5f71"], "create_at": "2017-09-11", "reply_count": "3"}, {"href": "/bbs/thread/e5df87736ffe7128/66531659-1.html", "topic": "\r\n\u5408\u540c\u7b7e\u5b8c\u4e4b\u540e\u53c8\u8ba9\u52a0\u88c5\u9970\uff0c\u6211\u4e0d\u540c\u610f\u53ef\u4ee5\u6295\u8bc9\u5417\uff1f            ", "author": ["//i.autohome.com.cn/39792052", "\u4e0a\u4e0a\ufffdL"], "create_at": "2017-09-11", "reply_count": "21"}, {"href": "/bbs/thread/d7e510c74544639c/66537893-1.html", "topic": "\r\n\u5e7f\u5dde9\u6708\u56e2\u8d2d\u8282\uff0c\u8001\u53f8\u673a\u6765\u770b\u770b            ", "author": ["//i.autohome.com.cn/55923183", "\u52c7\u5f80\u76f4\u524d357"], "create_at": "2017-09-11", "reply_count": "2"}, {"href": "/bbs/thread/ba2fb92157673d86/66533106-1.html", "topic": "\r\n\u95ee\u95ee\u5927\u5bb6\u81ea\u8c6a\u6539\u706f\u95ee\u9898            ", "author": ["//i.autohome.com.cn/3772466", "\u675c\u666f\u6ee1"], "create_at": "2017-09-11", "reply_count": "9"}, {"href": "/bbs/thread/ca67c6552e3a4e7d/66509408-1.html", "topic": "\r\n\u4eca\u5929\u8ba2\u8f66\uff0c\u6211\u4e5f\u52a0\u5165\u5c0f\u601d\u7b49\u5f85\u7684\u961f\u4f0d\u91cc\u4e86\uff01            ", "author": ["//i.autohome.com.cn/31907552", "\u5f88\u9177\u5f88\u9177\u7684\u7537\u8d85\u4eba"], "create_at": "2017-09-10", "reply_count": "11"}, {"href": "/bbs/thread/ac4cbee23a7175eb/66470464-1.html", "topic": "\r\n11111122222222211            ", "author": ["//i.autohome.com.cn/38159044", "\u9093Ethan"], "create_at": "2017-09-09", "reply_count": "4"}, {"href": "/bbs/thread/eb771c43c023705c/66530015-1.html", "topic": "\r\n\u8c01\u6d17\u8fc7\u53d1\u52a8\u673a\u8231\uff1f            ", "author": ["//i.autohome.com.cn/41540869", "Ayebye"], "create_at": "2017-09-11", "reply_count": "5"}, {"href": "/bbs/thread/55b973eea5f77e52/66537522-1.html", "topic": "\r\n\u8bba\u575b\u5f00\u4e0d\u4e86            ", "author": ["//i.autohome.com.cn/20911561", "\u7231\u8f66\u4e4b\u795e\u54c7"], "create_at": "2017-09-11", "reply_count": "4"}, {"href": "/bbs/thread/4e03e99ace4b8340/66533431-1.html", "topic": "\r\n\u91d1\u534e\u601d\u57df\u7535\u6298\u8033\u90a3\u91cc\u6709\u6539\u88c5\u7684\uff1f            ", "author": ["//i.autohome.com.cn/37859229", "wqnmgjb"], "create_at": "2017-09-11", "reply_count": "1"}, {"href": "/bbs/thread/8b5620a61cd86019/66427512-1.html", "topic": "\r\n\u601d\u57df1.0\u8f66\u4e3b\u8bf7\u8fdb\uff01            ", "author": ["//i.autohome.com.cn/28687171", "\u5403\u74dc\u7fa4\u4f17\u8868\u793a\u8d5e\u540c"], "create_at": "2017-09-07", "reply_count": "36"}, {"href": "/bbs/thread/7239d6f76794692a/66534219-1.html", "topic": "\r\n\u601d\u57df\u5c3e\u706f\u591a\u5c11\u94b1\uff1f            ", "author": ["//i.autohome.com.cn/1531820", "cynever"], "create_at": "2017-09-11", "reply_count": "6"}, {"href": "/bbs/thread/bd8e7c7374d819d7/66397799-1.html", "topic": "\r\n\u8c01\u51fa9\u4ee3\u601d\u57df            ", "author": ["//i.autohome.com.cn/16996635", "qczj415263"], "create_at": "2017-09-06", "reply_count": "8"}, {"href": "/bbs/thread/1420082674cb0c33/66526952-1.html", "topic": "\r\n\u3010\u8bb0\u5f55\u5962\u4f88\u5bbd\u4f53\u8f7f\u8dd1\u8e6d\u6211\u5927\u601d\u57df\u4e8b\u4ef6\u3011            ", "author": ["//i.autohome.com.cn/8994212", "\u7231\u4f60\u6ca1\u5deeJ"], "create_at": "2017-09-11", "reply_count": "5"}, {"href": "/bbs/thread/1444322e3b8de765/64631953-1.html", "topic": "\r\n\u601d\u57df\u9996\u4fdd\u4f60\u4eec\u662f\u591a\u4e45\u7684            ", "author": ["//i.autohome.com.cn/40673515", "\u99a8\u99a834"], "create_at": "2017-07-08", "reply_count": "4"}, {"href": "/bbs/thread/35248330bba639f0/65503438-1.html", "topic": "\r\n\u5355\u5df2\u8f6c\uff0c\u52ff\u6270            ", "author": ["//i.autohome.com.cn/29334406", "\u4e1c\u839e\u8001"], "create_at": "2017-08-08", "reply_count": "50"}, {"href": "/bbs/thread/172b5621c61dac1d/66535024-1.html", "topic": "\r\n\u8d37\u6b3e\u4e70\u7684\u601d\u57df\uff0c\u5927\u5bb6\u5e2e\u6211\u770b\u770b\u8fd9\u4e2a\u4fdd\u9669\u5355\u6709\u5565\u95ee\u9898\u6ca1\u3002\u672c\u4eba\u5c0f\u767d            ", "author": ["//i.autohome.com.cn/53094685", "\u6768\u5175\u51756"], "create_at": "2017-09-11", "reply_count": "5"}, {"href": "/bbs/thread/5415589bbd70217c/66529153-1.html", "topic": "\r\n\u5927\u5bb6\u5e02\u533a\u6cb9\u8017\u90fd\u591a\u5c11\uff1f            ", "author": ["//i.autohome.com.cn/33058137", "\u513f\u7ae5\u4f55"], "create_at": "2017-09-11", "reply_count": "4"}, {"href": "/bbs/thread/d3cce95345d6cc94/62073750-1.html", "topic": "\r\n\u4e5d\u4ee3\u66f4\u6362\u7ede\u7259\u907f\u9707\uff0c\u964d\u4f4e\u8f66\u8eab\u540e\u7684\u95ee\u9898\uff01[\u674e\u5b50\u4e32\u7bc7]            ", "author": ["//i.autohome.com.cn/4430732", "\u5f90\u6653\u7fd4"], "create_at": "2017-04-08", "reply_count": "65"}, {"href": "/bbs/thread/11141e27e89c816e/66532829-1.html", "topic": "\r\n\u601d\u57df\u5c0a\u8d35\u7248\u8fd8\u662f\u96c5\u9601\u7cbe\u82f1\u7248\uff1f            ", "author": ["//i.autohome.com.cn/1547225", "\u554a\u6bdb\u6559\u6388"], "create_at": "2017-09-11", "reply_count": "13"}, {"href": "/bbs/thread/9b643fa531da5884/66533051-1.html", "topic": "\r\n\u8bf7\u95ee\u4f60\u4eec\u601d\u57df\u4fdd\u517b\u591a\u5c11\u94b1\u554a            ", "author": ["//i.autohome.com.cn/27746815", "hsy1115"], "create_at": "2017-09-11", "reply_count": "7"}, {"href": "/bbs/thread/3a2eacc22ed35dec/66534436-1.html", "topic": "\r\n\u601d\u57df\u5728\u9ad8\u901f\u884c\u9a76\u65f6\u3002            ", "author": ["//i.autohome.com.cn/57364598", "\u4e13\u4e1a\u65c5\u6e38\u987e\u95ee"], "create_at": "2017-09-11", "reply_count": "5"}, {"href": "/bbs/thread/2fa5c8969b442cad/64056856-1.html", "topic": "\r\n\u672c\u4ee5\u4e3a\u4e0d\u4f1a\u53d1\u751f\u5728\u81ea\u5df1\u8eab\u4e0a\uff0c\u6ca1\u60f3\u5230\u4e2d\u67aa\u4e86\uff0c\u5168\u8f66\u6545\u969c\u706f\u4eae            ", "author": ["//i.autohome.com.cn/12010334", "\u7f18\u5206\u51b3\u5b9a\u4e00\u5207"], "create_at": "2017-06-17", "reply_count": "75"}, {"href": "/bbs/thread/f17ee21b9fa2607e/66529912-1.html", "topic": "\r\n2\u5c0f\u65f6\u7684\u6210\u679c\u54c8\u54c8\u54c8\u54c8\u54c8\u54c8\u54c8            ", "author": ["//i.autohome.com.cn/37262738", "LInCAnQIn"], "create_at": "2017-09-11", "reply_count": "8"}, {"href": "/bbs/thread/72914bee77fc5a9e/66524954-1.html", "topic": "\r\n\u5468\u672b\u64b8\u300a\u901f\u6fc0\u300b\uff0c\u4f60\u4eec\u731c\u901f1\u4e2d\u8bf4\u7684\u201c\u559c\u7f8e\u201d\u662f\u672c\u7530\u7684\u54ea\u4e00\u6b3e\uff1f            ", "author": ["//i.autohome.com.cn/53672174", "\u8f9b\u82e6\u722c\u683c\u5b50"], "create_at": "2017-09-11", "reply_count": "2"}, {"href": "/bbs/thread/27591a1c946dc1a2/66535131-1.html", "topic": "\r\n\u6c42\u6559\u6c42\u6559\uff01            ", "author": ["//i.autohome.com.cn/53109280", "\u5929\u8d50\u6de1\u96c5\u999911"], "create_at": "2017-09-11", "reply_count": "4"}, {"href": "/bbs/thread/e4524259eb52d8a1/66534312-1.html", "topic": "\r\n\u4e1c\u672c\u552e\u540e            ", "author": ["//i.autohome.com.cn/26981651", "hero9528"], "create_at": "2017-09-11", "reply_count": "6"}, {"href": "/bbs/thread/5580bed24c426a16/66533752-1.html", "topic": "\r\n15000\u516c\u91cc\u66f4\u6362\u673a\u6cb9            ", "author": ["//i.autohome.com.cn/30759486", "\u58a8\u8ff9\u9f99\u56fe\u817e"], "create_at": "2017-09-11", "reply_count": "2"}, {"href": "/bbs/thread/fdee8c38a648487f/66520723-1.html", "topic": "\r\n\u4e0e\u601d\u57df\u65e0\u7f18\uff01\u9047\u5230\u4e0d\u597d\u7684\u9500\u552e            ", "author": ["//i.autohome.com.cn/8775765", "lowenwu"], "create_at": "2017-09-11", "reply_count": "9"}, {"href": "/bbs/thread/39d12f2ea4024b22/66536530-1.html", "topic": "\r\n\u601d\u57df\u6309\u63ed\u95ee\u9898            ", "author": ["//i.autohome.com.cn/37703122", "20\u96c6"], "create_at": "2017-09-11", "reply_count": "2"}, {"href": "/bbs/thread/4c9f51849777abcb/66513070-1.html", "topic": "\r\n\u51cc\u6e21230\u81ea\u52a8\u98ce\u9a9a\u548c\u601d\u57df\u81ea\u52a8\u8c6a\u534e\u90a3\u4e2a\u884c            ", "author": ["//i.autohome.com.cn/33279326", "\u6211\u7231\u6211\u5bb6ACE"], "create_at": "2017-09-10", "reply_count": "8"}, {"href": "/bbs/thread/227cb7806c1ad9a9/66536436-1.html", "topic": "\r\n\u6709\u6ca1\u670910\u6708\u4efd\u53ef\u4ee5\u63d01.5\u624b\u8c6a\u7684\u670b\u53cb            ", "author": ["//i.autohome.com.cn/56832030", "\u8d75\u6d69\u6749"], "create_at": "2017-09-11", "reply_count": "0"}, {"href": "/bbs/thread/fffa09f27572a245/66534472-1.html", "topic": "\r\n\u6709\u8c01\u77e5\u9053\u5341\u4ee3\u601d\u57df\u97f3\u54cd\u600e\u4e48\u8c03            ", "author": ["//i.autohome.com.cn/53474916", "\u534a\u4e2a\u597d\u4eba1"], "create_at": "2017-09-11", "reply_count": "4"}, {"href": "/bbs/thread/adcaa230b081f8bc/66525231-1.html", "topic": "\r\n\u601d\u57df\u4fdd\u517b\u673a\u6cb9\u95ee\u9898            ", "author": ["//i.autohome.com.cn/17135813", "\u6c7e\u6cb3\u7554\u5c0f\u9cb8\u9c7c"], "create_at": "2017-09-11", "reply_count": "10"}, {"href": "/bbs/thread/68ffcbadfe6e87a7/66511051-1.html", "topic": "\r\n\u4f60\u4eec\u8981\u4ec0\u4e48\u989c\u8272            ", "author": ["//i.autohome.com.cn/24324317", "\u632f\u5927\u5e05\u54e5"], "create_at": "2017-09-10", "reply_count": "33"}, {"href": "/bbs/thread/9e3663b9d2fea5cf/66530420-1.html", "topic": "\r\n\u5927\u5bb6\u6765\u5e2e\u5fd9            ", "author": ["//i.autohome.com.cn/42149299", "\u7136\u7136\u7238\u7238\u7231\u4f60"], "create_at": "2017-09-11", "reply_count": "7"}, {"href": "/bbs/thread/c966d0decd96c47a/66531669-1.html", "topic": "\r\n12\u6b3e\u601d\u57df\u53d8\u901f\u7bb1\u6cb9            ", "author": ["//i.autohome.com.cn/16211205", "cool\u6de1\u5357"], "create_at": "2017-09-11", "reply_count": "4"}, {"href": "/bbs/thread/8d270541cda16de5/64506778-1.html", "topic": "\r\nhonda nine civic  for k20            ", "author": ["//i.autohome.com.cn/9624833", "\u7ca4TTW210"], "create_at": "2017-07-03", "reply_count": "31"}, {"href": "/bbs/thread/43ce9812b2876c8a/66533850-1.html", "topic": "\r\n\u5341\u4ee3\u601d\u57df \u6da1\u8f6e\u591a\u5c11\u8f6c\u4ecb\u5165\uff1f            ", "author": ["//i.autohome.com.cn/39014018", "\u6c99\ufffd\ufffd"], "create_at": "2017-09-11", "reply_count": "2"}, {"href": "/bbs/thread/f421300c04c3325b/66530164-1.html", "topic": "\r\n\u54ea\u4f4d\u5144\u5f1f\u5728\u5e7f\u5dde4S\u5e97\u6709\u719f\u4eba\u7684\u3002            ", "author": ["//i.autohome.com.cn/56924767", "\ufffd\u4ed3\ufffd\u6240\u5411"], "create_at": "2017-09-11", "reply_count": "7"}, {"href": "/bbs/thread/a86f281a8a18598b/66534783-1.html", "topic": "\r\n\u4eca\u5929\u8ba2\u8f66\u5566            ", "author": ["//i.autohome.com.cn/40200927", "343aa"], "create_at": "2017-09-11", "reply_count": "5"}, {"href": "/bbs/thread/5dc3458d7bda74b3/66529147-1.html", "topic": "\r\n\u8bf7\u95ee\u5927\u795e \u8fd9\u4e2a\u662f\u4ec0\u4e48\u8131\u843d\u4e86\uff1f\u4e25\u91cd\u5417            ", "author": ["//i.autohome.com.cn/53636444", "\u7ca5\u4f69\u4f69"], "create_at": "2017-09-11", "reply_count": "9"}, {"href": "/bbs/thread/aedbbef025cd399b/66446890-1.html", "topic": "\r\n\u8fd9\u8f6e\u80ce\u9700\u8981\u6362\u5417\uff1f            ", "author": ["//i.autohome.com.cn/37127159", "\u5927\u867e\u4e24\u53ea\u82b1"], "create_at": "2017-09-08", "reply_count": "14"}, {"href": "/bbs/thread/ba9fc14d45c6d2cf/66532150-1.html", "topic": "\r\n\u65b0\u601d\u8d28\u91cf\u6760\u6760\u6ef4            ", "author": ["//i.autohome.com.cn/37852351", "\u5f85\u71c3\u7684\u9999\u70df"], "create_at": "2017-09-11", "reply_count": "22"}, {"href": "/bbs/thread/6bf4f3c432e6a1a0/66534478-1.html", "topic": "\r\n\u6c42\u52a9\uff0c\u6c42\u52a9\uff0c\u53ea\u66f4\u6362\u5927\u5239\u8f66\u76d8\u5b50\u53ef\u4ee5\u5417\uff1f            ", "author": ["//i.autohome.com.cn/27189517", "\u8d75\u9e4fsuper\u98de"], "create_at": "2017-09-11", "reply_count": "2"}, {"href": "/bbs/thread/6902276ab6cf1451/66528050-1.html", "topic": "\r\n\u7ecf\u8fc720\u591a\u5929\u7684\u7b49\u5f85\u7ec8\u4e8e\u63d0\u8f66\uff01\u5750\u6807\u6210\u90fd            ", "author": ["//i.autohome.com.cn/5614286", "\u9e2d\u54e5\u4e0d\u662f\u9e2d\u5b50"], "create_at": "2017-09-11", "reply_count": "28"}, {"href": "/bbs/thread/415a52013b34b5b3/66534351-1.html", "topic": "\r\n\u6c42\u8d2d\u516b\u4ee3\u601d\u57df\u539f\u88c5\u8f6e\u6bc2            ", "author": ["//i.autohome.com.cn/12019525", "\u6e29\u5dde\u6f58\u6865\u56fd\u9645\u6c7d\u8f66\u57ce"], "create_at": "2017-09-11", "reply_count": "0"}, {"href": "/bbs/thread/06f27e8b2873a67f/66364377-1.html", "topic": "\r\n\u5341\u4ee3\u601d\u57df\uff0c\u81ea\u8c6a\u7248\uff0c\u5927\u5bb6\u8fc7\u6765\u56f4\u89c2\u4e0b            ", "author": ["//i.autohome.com.cn/56114256", "\u56f4\u57cel"], "create_at": "2017-09-05", "reply_count": "22"}, {"href": "/bbs/thread/a3273de53f66ef5b/66520518-1.html", "topic": "\r\nbrakehold\uff0c\u6bcf\u6b21\u90fd\u8981\u624b\u52a8\u5f00\u542f\u5417\uff1f            ", "author": ["//i.autohome.com.cn/30287354", "\u5e26\u72d7\u770b\u897f\u9633"], "create_at": "2017-09-11", "reply_count": "9"}, {"href": "/bbs/thread/a27a65ffaa94d71d/66532239-1.html", "topic": "\r\n\u6025\u6025\u6025\uff0c\u90d1\u5dde\u8f66\u53cb\u3002            ", "author": ["//i.autohome.com.cn/14111281", "\u72fc\u5b50\u91ce\u5fc3\u4e36"], "create_at": "2017-09-11", "reply_count": "3"}, {"href": "/bbs/thread/97bb624dcdb84bd6/66532462-1.html", "topic": "\r\n\u601d\u57df\u7684\u6c34\u7bb1\u591a\u4e45\u52a0\u4e00\u6b21\u7684\uff1f\u4e0d\u5230\u4e00\u5e74\u51fa\u73b0\u6c34\u7bb1\u5e72\u4e86\u7684\u6c34\u6e29\u7206\u8868\u73b0\u8c61            ", "author": ["//i.autohome.com.cn/51331662", "lanPL971"], "create_at": "2017-09-11", "reply_count": "5"}, {"href": "/bbs/thread/5460d9c4cfe206e2/66511910-1.html", "topic": "\r\n\u4eca\u65e5\u5df2\u8ba2\u601d\u57df\uff0c\u5927\u5bb6\u770b\u770b\u4ef7\u683c\u600e\u4e48\u6837\uff1f            ", "author": ["//i.autohome.com.cn/8832897", "\u9ed1\u8272\u9177\u4ed4"], "create_at": "2017-09-10", "reply_count": "7"}, {"href": "/bbs/thread/3d8fe4555486a29c/66532131-1.html", "topic": "\r\n\u5173\u4e8e\u8f66\u5f88\u5927\u7684\u95ee\u9898            ", "author": ["//i.autohome.com.cn/30464516", "bentianshidaisiyu"], "create_at": "2017-09-11", "reply_count": "5"}, {"href": "/bbs/thread/c1cca168aa07bb76/66531672-1.html", "topic": "\r\n\u63d0\u8f66\u4e86\uff0c\u540e\u7eed\u66f4\u65b0\uff0c\u7b49\u4e8646\u5929            ", "author": ["//i.autohome.com.cn/54494108", "Evil\u4e36alex"], "create_at": "2017-09-11", "reply_count": "2"}, {"href": "/bbs/thread/c01dbc5d9ac7088c/66520299-1.html", "topic": "\r\n\u5b81\u6ce2\u5730\u533a\u601d\u57df\u53c2\u8003            ", "author": ["//i.autohome.com.cn/56234443", "\u5ba4\u5185\u6843\u56ed"], "create_at": "2017-09-11", "reply_count": "10"}, {"href": "/bbs/thread/09a8652ab64efe3a/66368485-1.html", "topic": "\r\n\u5173\u4e8e\u601d\u57df\u81ea\u8c6a\uff0c\u5750\u6807 \u5e7f\u4e1c\u6c5f\u95e8            ", "author": ["//i.autohome.com.cn/37194300", "\u5e7f\u4e1c\u85e4\u539f\u62d3\u6d77"], "create_at": "2017-09-05", "reply_count": "24"}, {"href": "/bbs/thread/0f11d323d7f09b35/66529659-1.html", "topic": "\r\n\u90fd\u8bf4\u8bf4\u4f60\u4eec\u7684\u4fdd\u9669\u591a\u5c11\u94b1            ", "author": ["//i.autohome.com.cn/16137945", "\u67d2\u591c75"], "create_at": "2017-09-11", "reply_count": "8"}, {"href": "/bbs/thread/da1956de99282ab0/66519363-1.html", "topic": "\r\n\u601d\u57df\u601d\u57df\u7684\u95ee\u9898            ", "author": ["//i.autohome.com.cn/23778479", "\u597d\u4eba\u597d\u4e8b\u591a"], "create_at": "2017-09-11", "reply_count": "8"}, {"href": "/bbs/thread/93287d792bba3ad7/66527851-1.html", "topic": "\r\n\u601d\u57df\u542f\u52a8\u8bfb\u6b4c\u95ee\u9898            ", "author": ["//i.autohome.com.cn/54582975", "\u9b54\u5e7b\u7d2b\u82721"], "create_at": "2017-09-11", "reply_count": "7"}, {"href": "/bbs/thread/c71b365acaaca9c7/66529059-1.html", "topic": "\r\n\u601d\u57df\u5356\u4e86\u6709\u4eba\u8981\u5417            ", "author": ["//i.autohome.com.cn/34264665", "\u6c5f\u4ec1\u5fe0"], "create_at": "2017-09-11", "reply_count": "17"}, {"href": "/bbs/thread/5198d7cf56ac7d4d/66528886-1.html", "topic": "\r\n\u5c0a\u8d35\u7248\u843d\u5730\u591a\u5c11\uff1f            ", "author": ["//i.autohome.com.cn/57353719", "\u626b\u4e8c\u7ef4\u7801"], "create_at": "2017-09-11", "reply_count": "9"}, {"href": "/bbs/thread/16d56d67b9cdc6ba/66390133-1.html", "topic": "\r\n\u6211\u7684\u6697\u91d1\u84dd\u5929\u5929\u591a\u662f\u8fd9\u4e48\u4eae\uff01            ", "author": ["//i.autohome.com.cn/23322476", "dorrom"], "create_at": "2017-09-06", "reply_count": "33"}, {"href": "/bbs/thread/19ec7882018c1f72/66532988-1.html", "topic": "\r\n7\u4e07\u4ebf\u5e02\u573a\u6765\u4e86\uff01\u65e0\u4eba\u8f66\u5728\u672a\u6765\u4f1a\u6709\u4ec0\u4e48\u6837\u7684\u5e94\u7528\u573a\u666f\uff1f            ", "author": ["//i.autohome.com.cn/56927889", "\u6234\u5609\u6167"], "create_at": "2017-09-11", "reply_count": "0"}, {"href": "/bbs/thread/a850708b6cc908a2/66529473-1.html", "topic": "\r\n\u5efa\u884c\u8fd9\u4e2a\u6709\u7528\u5417            ", "author": ["//i.autohome.com.cn/37668419", "\u8d64\u88f8\u88f8\u7684\u8bf1\u60d1x"], "create_at": "2017-09-11", "reply_count": "8"}, {"href": "/bbs/thread/9fc42b55e093c0d2/66528344-1.html", "topic": "\r\n\u540e\u5c3e\u7bb1\u6709\u95ee\u9898\u3002            ", "author": ["//i.autohome.com.cn/38001288", "\u82f1\u4fca\u6f47\u6d12\u624d\u534e\u6a2a\u6ea2"], "create_at": "2017-09-11", "reply_count": "5"}, {"href": "/bbs/thread/9464a3dd81dcd1a2/66507685-1.html", "topic": "\r\n\u516b\u4ee3\u601d\u57df\u65b9\u5411\u6253\u65b9\u5411\u4f1a\u5f88\u91cd\u5417            ", "author": ["//i.autohome.com.cn/55303696", "JIANHUI_CHAN"], "create_at": "2017-09-10", "reply_count": "9"}, {"href": "/bbs/thread/f73a759fcbbdc46e/66523549-1.html", "topic": "\r\n\u601d\u57df\u4e3a\u4f551.0T\u624b\u52a8\u6700\u9ad8204\uff0c1.5T\u81ea\u5c0a\u6700\u9ad8\u624d200            ", "author": ["//i.autohome.com.cn/29153117", "\u6211\u5c31\u9759\u9759\u7684\u770b\u7740\u4f60\u88c513"], "create_at": "2017-09-11", "reply_count": "13"}, {"href": "/bbs/thread/52d8e1bfc305a650/66532313-1.html", "topic": "\r\n\u884c\u8f66\u8bb0\u5f55\u4eea            ", "author": ["//i.autohome.com.cn/27204300", "\u8884\u597d\u7231\u4f60"], "create_at": "2017-09-11", "reply_count": "4"}, {"href": "/bbs/thread/9a3be9c0b0fb1ed9/66516456-1.html", "topic": "\r\n\u6211\u6709\u53e5mmp\u5fc5\u987b\u5f97\u8bb2\uff0c            ", "author": ["//i.autohome.com.cn/46794600", "\u50bb\u50bb\u50bb\u50bb\u5218\u4e36"], "create_at": "2017-09-10", "reply_count": "11"}, {"href": "/bbs/thread/7267b68702e620c6/66531505-1.html", "topic": "\r\n\u4eca\u5929\u624d\u77e5\u9053\uff0c\u539f\u6765\u5b83\u7684\u6bcf\u4e00\u6b21\u90fd\u90a3\u4e48\u91cd\u8981\uff01            ", "author": ["//i.autohome.com.cn/42262519", "jay12356"], "create_at": "2017-09-11", "reply_count": "2"}, {"href": "/bbs/thread/b0aaabf3903ceee8/66515886-1.html", "topic": "\r\n\u6ca1\u4e8b\u5c31\u7231\u6765\u601d\u57df\u8bba\u575b\u901b\u901b            ", "author": ["//i.autohome.com.cn/29639495", "\u4f73\u8f89\u963f"], "create_at": "2017-09-10", "reply_count": "12"}, {"href": "/bbs/thread/772ce1797941c43f/66432226-1.html", "topic": "\r\n\u65b0\u8fdb\u4e0d\u4e45\u7684\u601d\u57df8\uff0c\u6536\u4e86\u4e2a6\u789fCD\uff0c\u7adf\u7136\u4e0d\u77e5\u9053\u9762\u677f\u4ece\u54ea\u62c6\u8d77\u3002\u3002\u3002            ", "author": ["//i.autohome.com.cn/5011935", "\u5fae\u5c18668"], "create_at": "2017-09-08", "reply_count": "3"}, {"href": "/bbs/thread/c92196ce32bcde8a/66524774-1.html", "topic": "\r\n\u8fd9\u4e2a\u4e09\u6ee4\u914d\u4ef6\u9760\u8c31\u5417\uff0c\u5927\u5bb6\u6765\u8bf4\u8bf4\u3002            ", "author": ["//i.autohome.com.cn/30553254", "Tracy\u6e29\u51c9"], "create_at": "2017-09-11", "reply_count": "14"}, {"href": "/bbs/thread/9c624f3f8cd54eba/66528879-1.html", "topic": "\r\n\u516b\u4ee3\u601d\u57df\u76ae\u5e26\u67091960\uff0c2164\uff0c2170\u4e09\u79cd\u957f\u5ea6\uff0c\u771f\u4e0d\u77e5\u9053            ", "author": ["//i.autohome.com.cn/35471052", "LSJ\u987a"], "create_at": "2017-09-11", "reply_count": "1"}, {"href": "/bbs/thread/9db59215bee45b8d/66497833-1.html", "topic": "\r\n\u7ea0\u7ed3\u70e6\u6b7b\u4e86\u600e\u4e48\u529e\uff1f            ", "author": ["//i.autohome.com.cn/23778479", "\u597d\u4eba\u597d\u4e8b\u591a"], "create_at": "2017-09-10", "reply_count": "17"}, {"href": "/bbs/thread/ff58b3742166c54f/66512397-1.html", "topic": "\r\n\u63d0\u8f66\u4e00\u4e2a\u6708\uff0c1500KM\u3002  \u8fd9\u4e2a\u6cb9\u8017\u611f\u89c9\u548b\u6837\u3002            ", "author": ["//i.autohome.com.cn/38257846", "\u7231\u83ab\u80fd\u52a91010"], "create_at": "2017-09-10", "reply_count": "20"}, {"href": "/bbs/thread/48905f9680eb569f/66510931-1.html", "topic": "\r\n\u4e0a\u5348\u7684\u5e16\u5b50\u8fd8\u70ed\u4e4e\uff0c\u8fd9\u4e2a\u5e16\u5b50\u53c8\u6765\u4e86\uff0c\u5341\u5929\u7b2c\u4e00\u649e\uff0c\u6559\u5e08\u8282\u793c\u7269\uff1f\uff1f            ", "author": ["//i.autohome.com.cn/9049671", "\u4e70\u4e2a\u4e8c\u624b\u98de\u673a"], "create_at": "2017-09-10", "reply_count": "9"}, {"href": "/bbs/thread/d2b4e3b0e99ab990/66528514-1.html", "topic": "\r\n\u5341\u4ee3\u601d\u57df\u706f\u5149\u95ee\u9898            ", "author": ["//i.autohome.com.cn/32081531", "\u62e7\u58f6\u51b2007"], "create_at": "2017-09-11", "reply_count": "9"}, {"href": "/bbs/thread/a389bffb1660475c/66528962-1.html", "topic": "\r\n\u601d\u57df\u5206\u671f\u8d37\u6b3e\u4e70\u8f66\u7684\u624b\u7eed\u8d39\u90fd\u662f\u591a\u5c11\u554a\uff1f\uff1f            ", "author": ["//i.autohome.com.cn/27500002", "flow77"], "create_at": "2017-09-11", "reply_count": "3"}, {"href": "/bbs/thread/9a5ea6b0349ec69a/66494331-1.html", "topic": "\r\n\u897f\u5b89\u54ea\u91cc\u4e0d\u52a0\u4ef7\uff01            ", "author": ["//i.autohome.com.cn/37987039", "\u5b89\u9038de\u61d2\u6d0b\u6d0b"], "create_at": "2017-09-10", "reply_count": "18"}, {"href": "/bbs/thread/48c0699178c66b8a/66495367-1.html", "topic": "\r\n\u81ea\u8c6a\u6539\u5927\u706f\u54ea\u79cd\u6027\u4ef7\u6bd4\u9ad8            ", "author": ["//i.autohome.com.cn/39608029", "\u57df\u7bad"], "create_at": "2017-09-10", "reply_count": "20"}, {"href": "/bbs/thread/a41d1278f30aeaef/61969516-1.html", "topic": "\r\n\u4e1c\u672c\u9ed1\u6876\u5168\u5408\u62100W20\u673a\u6cb9            ", "author": ["//i.autohome.com.cn/9921013", "200923099"], "create_at": "2017-04-04", "reply_count": "34"}, {"href": "/bbs/thread/bc09fbb8f3f3cfd7/66530365-1.html", "topic": "\r\n\u601d\u57df\u8d37\u6b3e\u662f\u600e\u4e48\u6837\u7684\uff1f            ", "author": ["//i.autohome.com.cn/35856067", "\u97e6\u712f\u6cfd"], "create_at": "2017-09-11", "reply_count": "1"}, {"href": "/bbs/thread/f30daab0f89304ee/66523319-1.html", "topic": "\r\n4s\u5e97\u4fdd\u517b\u52a05w-40\u7684\u673a\u6cb9 \u611f\u89c9\u6cb9\u8017\u4e0a\u53bb\u4e86\uff0c\u5230\u5e95\u52a0\u4ec0\u4e48\u673a\u6cb9\u5408\u9002\uff1f            ", "author": ["//i.autohome.com.cn/19678821", "Zlive1990"], "create_at": "2017-09-11", "reply_count": "20"}, {"href": "/bbs/thread/8eca94aecba75673/66531069-1.html", "topic": "\r\n\u5341\u4ee3\u601d\u57df            ", "author": ["//i.autohome.com.cn/38608608", "\ufffd\u69df\ufffd\ufffd\u8238\ufffd"], "create_at": "2017-09-11", "reply_count": "0"}, {"href": "/bbs/thread/ced4e801d8a089d0/66516204-1.html", "topic": "\r\n\u4e0b\u96e8\u540e\u89c6\u955c\u770b\u4e0d\u6e05            ", "author": ["//i.autohome.com.cn/37578287", "\u751c\u679c\u7684\u68a6\u60f3"], "create_at": "2017-09-10", "reply_count": "12"}, {"href": "/bbs/thread/b1f483e113c24433/66518218-1.html", "topic": "\r\n\u601d\u57df\u548c\u5929\u7c41\u6539\u6b3e\u8212\u9002\u7248\u5bf9\u6bd4\uff0c\u6c42\u610f\u89c1\u3002            ", "author": ["//i.autohome.com.cn/37795945", "\u6db5\u6db5\u599e"], "create_at": "2017-09-11", "reply_count": "24"}, {"href": "/bbs/thread/4b0e3e2a1ea6895c/65694895-1.html", "topic": "\r\n\u77e5\u9053\u5728\u65e5\u672c\u4eba\u7684\u773c\u91cc\u662f\u600e\u4e48\u770b\u5fb7\u7cfb\u8f66\u7684\u5417            ", "author": ["//i.autohome.com.cn/30440517", "zhangxueyoujac"], "create_at": "2017-08-14", "reply_count": "14"}, {"href": "/bbs/thread/2c561b8b4e51bb8a/66529080-1.html", "topic": "\r\n\u81ea\u8c6a\u9a9a\u84dd\u8f6e\u6bc2\u914d\u9ed1\u95ee\u9898            ", "author": ["//i.autohome.com.cn/56258018", "\u742a\u7b11\u8a00\u5f00"], "create_at": "2017-09-11", "reply_count": "1"}]